kimpoet/__init__.py
kimpoet/kimpoet.py
kimpoet-24863.28.10.dist-info/METADATA
kimpoet-24863.28.10.dist-info/WHEEL
kimpoet-24863.28.10.dist-info/top_level.txt
kimpoet-24863.28.10.dist-info/RECORD
