Metadata-Version: 2.1
Name: kimpoet
Version: 24863.28.10
Summary: the package is used to define poets
Home-page: UNKNOWN
Author: pycreaterset
Author-email: 13816349024@139.com
License: UNKNOWN
Platform: UNKNOWN
Classifier: Programming Language :: Python :: 3.5
Classifier: Programming Language :: Python :: 3.6
Classifier: Programming Language :: Python :: 3.7
Classifier: Programming Language :: Python :: 3.8
Classifier: Programming Language :: Python :: 3.9
Classifier: Programming Language :: Python :: 3.10
